stats211/__init__.py
stats211/confidence_intervals.py
stats211/critical_values.py
stats211/descriptive.py
stats211/hypothesis_testing.py
stats211/inverse.py
stats211/probability.py
stats211/regression.py
stats211/sample_size.py
stats211/standard_error.py
stats211/stats.py
stats211/two_sample.py
stats211/utils.py
stats211-0.1.4.dist-info/licenses/LICENSE
stats211-0.1.4.dist-info/METADATA
stats211-0.1.4.dist-info/WHEEL
stats211-0.1.4.dist-info/top_level.txt
stats211-0.1.4.dist-info/RECORD
